railscookie.py
railscookie-1.0.0.dist-info/DESCRIPTION.rst
railscookie-1.0.0.dist-info/METADATA
railscookie-1.0.0.dist-info/RECORD
railscookie-1.0.0.dist-info/WHEEL
railscookie-1.0.0.dist-info/metadata.json
railscookie-1.0.0.dist-info/top_level.txt
